setup.py
easycrud/__init__.py
easycrud/asgi.py
easycrud/settings.py
easycrud/urls.py
easycrud/wsgi.py
mycrudapp/__init__.py
mycrudapp/admin.py
mycrudapp/apps.py
mycrudapp/models.py
mycrudapp/serializers.py
mycrudapp/tests.py
mycrudapp/urls.py
mycrudapp/views.py
mycrudapp.egg-info/PKG-INFO
mycrudapp.egg-info/SOURCES.txt
mycrudapp.egg-info/dependency_links.txt
mycrudapp.egg-info/requires.txt
mycrudapp.egg-info/top_level.txt
mycrudapp/migrations/0001_initial.py
mycrudapp/migrations/__init__.py