Metadata-Version: 2.1
Name: mycrudapp
Version: 0.1
Classifier: Programming Language :: Python :: 3
Classifier: Framework :: Django
Classifier: Framework :: Django :: 3.2
Classifier: Operating System :: OS Independent
Requires-Dist: Django>=3.2
Requires-Dist: djangorestframework
